README.md
setup.py
calculator_cwl/__init__.py
calculator_cwl/__main__.py
calculator_cwl.egg-info/PKG-INFO
calculator_cwl.egg-info/SOURCES.txt
calculator_cwl.egg-info/dependency_links.txt
calculator_cwl.egg-info/top_level.txt