Metadata-Version: 2.1
Name: calculator-cwl
Version: 1.2
Summary: A Python Package Which does basic math calculation
Home-page: https://github.com/codewithlaksh/calculator_cwl
Author: CodeWithLaksh
Author-email: dashlakshyaraj2006@gmail.com
Classifier: Programming Language :: Python :: 3
